spatialx_connector/__init__.py
spatialx_connector/_analysis.py
spatialx_connector/_api.py
spatialx_connector/_connector.py
spatialx_connector/_constants.py
spatialx_connector/_utils.py
spatialx_connector-0.1.5.dist-info/METADATA
spatialx_connector-0.1.5.dist-info/WHEEL
spatialx_connector-0.1.5.dist-info/top_level.txt
spatialx_connector-0.1.5.dist-info/RECORD
