Metadata-Version: 2.1
Name: spatialx_connector
Version: 0.1.5
Summary: BioTuring SpatialX Connector
Home-page: https://alpha.bioturing.com
Author: BioTuring
Author-email: support@bioturing.com
Requires-Dist: pydantic==2.7.2
Requires-Dist: requests==2.32.3
Requires-Dist: tqdm==4.66.4
